kalabash_rspamd/__init__.py
kalabash_rspamd/admin.py
kalabash_rspamd/app_settings.py
kalabash_rspamd/apps.py
kalabash_rspamd/handlers.py
kalabash_rspamd/kbash_extension.py
kalabash_rspamd/models.py
kalabash_rspamd/tests.py
kalabash_rspamd/views.py
kalabash_rspamd/api/__init__.py
kalabash_rspamd/api/v2/__init__.py
kalabash_rspamd/api/v2/serializers.py
kalabash_rspamd/locale/br/LC_MESSAGES/django.mo
kalabash_rspamd/locale/br/LC_MESSAGES/django.po
kalabash_rspamd/locale/cs/LC_MESSAGES/django.mo
kalabash_rspamd/locale/cs/LC_MESSAGES/django.po
kalabash_rspamd/locale/cs_CZ/LC_MESSAGES/django.mo
kalabash_rspamd/locale/cs_CZ/LC_MESSAGES/django.po
kalabash_rspamd/locale/de/LC_MESSAGES/django.mo
kalabash_rspamd/locale/de/LC_MESSAGES/django.po
kalabash_rspamd/locale/de_DE/LC_MESSAGES/django.mo
kalabash_rspamd/locale/de_DE/LC_MESSAGES/django.po
kalabash_rspamd/locale/el_GR/LC_MESSAGES/django.mo
kalabash_rspamd/locale/el_GR/LC_MESSAGES/django.po
kalabash_rspamd/locale/en/LC_MESSAGES/django.mo
kalabash_rspamd/locale/en/LC_MESSAGES/django.po
kalabash_rspamd/locale/es/LC_MESSAGES/django.mo
kalabash_rspamd/locale/es/LC_MESSAGES/django.po
kalabash_rspamd/locale/fi/LC_MESSAGES/django.mo
kalabash_rspamd/locale/fi/LC_MESSAGES/django.po
kalabash_rspamd/locale/fr/LC_MESSAGES/django.mo
kalabash_rspamd/locale/fr/LC_MESSAGES/django.po
kalabash_rspamd/locale/hu/LC_MESSAGES/django.mo
kalabash_rspamd/locale/hu/LC_MESSAGES/django.po
kalabash_rspamd/locale/it/LC_MESSAGES/django.mo
kalabash_rspamd/locale/it/LC_MESSAGES/django.po
kalabash_rspamd/locale/ja_JP/LC_MESSAGES/django.mo
kalabash_rspamd/locale/ja_JP/LC_MESSAGES/django.po
kalabash_rspamd/locale/ka/LC_MESSAGES/django.mo
kalabash_rspamd/locale/ka/LC_MESSAGES/django.po
kalabash_rspamd/locale/nl_NL/LC_MESSAGES/django.mo
kalabash_rspamd/locale/nl_NL/LC_MESSAGES/django.po
kalabash_rspamd/locale/no/LC_MESSAGES/django.mo
kalabash_rspamd/locale/no/LC_MESSAGES/django.po
kalabash_rspamd/locale/pl_PL/LC_MESSAGES/django.mo
kalabash_rspamd-0.9.1.dist-info/LICENSE
kalabash_rspamd-0.9.1.dist-info/METADATA
kalabash_rspamd-0.9.1.dist-info/WHEEL
kalabash_rspamd-0.9.1.dist-info/top_level.txt
kalabash_rspamd-0.9.1.dist-info/RECORD
